epydemicarchive/__init__.py
epydemicarchive/api/v1/__init__.py
epydemicarchive/api/v1/routes.py
epydemicarchive/api/v1/client/__init__.py
epydemicarchive/api/v1/client/client.py
epydemicarchive/archive/__init__.py
epydemicarchive/archive/forms.py
epydemicarchive/archive/models.py
epydemicarchive/archive/queries.py
epydemicarchive/archive/routes.py
epydemicarchive/auth/__init__.py
epydemicarchive/auth/forms.py
epydemicarchive/auth/models.py
epydemicarchive/auth/routes.py
epydemicarchive/main/__init__.py
epydemicarchive/main/routes.py
epydemicarchive/metadata/__init__.py
epydemicarchive/metadata/analyser.py
epydemicarchive/metadata/ba.py
epydemicarchive/metadata/degreedistribution.py
epydemicarchive/metadata/er.py
epydemicarchive/metadata/hash.py
epydemicarchive/metadata/topology.py
epydemicarchive/user/__init__.py
epydemicarchive/user/forms.py
epydemicarchive/user/models.py
epydemicarchive/user/routes.py
epydemicarchive-0.2.1.dist-info/LICENSE
epydemicarchive-0.2.1.dist-info/METADATA
epydemicarchive-0.2.1.dist-info/WHEEL
epydemicarchive-0.2.1.dist-info/top_level.txt
epydemicarchive-0.2.1.dist-info/RECORD
